[
  {
    "Code": 75,
    "Name": "APC",
    "AddressLine1": "2425",
    "AddressLine2": "SE Oak Tree Court",
    "City": "ANKENY",
    "State": "IA",
    "CountryCode": "US",
    "Zip": "50021",
    "Phone": "515-289-7600",
    "Fax": "515-289-4360",
    "Email": "",
    "Logo": "",
    "CreatedBy": "SYSTEM",
    "CreatedOn": "2025-01-01T00:00:00"
  },
  {
    "Code": 82,
    "Name": "PROLIANT DAIRY",
    "AddressLine1": "2425",
    "AddressLine2": "SE Oak Tree Court",
    "City": "ANKENY",
    "State": "IA",
    "CountryCode": "US",
    "Zip": "50021",
    "Phone": "515-289-7600",
    "Fax": "515-289-4360",
    "Email": "",
    "Logo": "",
    "CreatedBy": "SYSTEM",
    "CreatedOn": "2025-01-01T00:00:00"
  },
  {
    "Code": 83,
    "Name": "ESSENTIA",
    "AddressLine1": "2425",
    "AddressLine2": "SE Oak Tree Court",
    "City": "ANKENY",
    "State": "IA",
    "CountryCode": "US",
    "Zip": "50021",
    "Phone": "515-289-7600",
    "Fax": "515-289-4360",
    "Email": "",
    "Logo": "",
    "CreatedBy": "SYSTEM",
    "CreatedOn": "2025-01-01T00:00:00"
  },
  {
    "Code": 84,
    "Name": "BIOLOGICALS",
    "AddressLine1": "2425",
    "AddressLine2": "SE Oak Tree Court",
    "City": "ANKENY",
    "State": "IA",
    "CountryCode": "US",
    "Zip": "50021",
    "Phone": "515-289-7600",
    "Fax": "515-289-4360",
    "Email": "",
    "Logo": "",
    "CreatedBy": "SYSTEM",
    "CreatedOn": "2025-01-01T00:00:00"
  }
]